Metadata-Version: 1.1
Name: Fool-house
Version: 1.1
Summary: Yellow house
Home-page: https://github.com/1Gregory/fool-house
Author: Andreew Gregory
Author-email: 6squaress@gmail.com
License: MIT
Download-URL: https://github.com/1Gregory/fool-house/archive/1.1.tar.gz
Keywords: YELLOW,FOOL,HOUSE,CORPSMAN,SCHIZO,COUNT
Platform: UNKNOWN
